{
  "name": "team_project",
  "plural": "team_project",
  "base": "PersistedModel",
  "idInjection": true,
  "options": {
    "validateUpsert": true
  },
  "postgresql": {
    "schema": "public",
    "table": "team_project"
  },
  "properties": {
    "id": {
      "type": "number",
      "required": false
    },
    "team_name": {
      "type": "string",
      "required": true
    }
  },
  "validations": [],
  "relations": {
    "user": {
      "type": "hasMany",
      "model": "user",
      "foreignKey": "team_name_id",
      "options": {
        "nestRemoting": true
      }
    },
     "task": {
      "type": "hasMany",
      "model": "task",
      "foreignKey": "team_name_id",
      "options": {
        "nestRemoting": true
      }
    }
  },
  "acls": [],
  "methods": {}
}
